<annotation>
	<folder>VOC2007</folder>
	<filename>banana015S(4).JPG</filename>
	<source>
		<database>My Database</database>
		<annotation>VOC2007</annotation>
		<image>flickr</image>
		<flickrid>NULL</flickrid>
	</source>
	<owner>
		<flickrid>NULL</flickrid>
		<name>Liang-yc</name>
	</owner>
	<size>
		<width>504</width>
		<height>378</height>
		<depth>3</depth>
	</size>
	<segmented>0</segmented>
	<object>
		<name>banana</name>
		<pose>Unspecified</pose>
		<truncated>0</truncated>
		<difficult>0</difficult>
		<bndbox>
			<xmin>52</xmin>
			<ymin>174</ymin>
			<xmax>335</xmax>
			<ymax>228</ymax>
		</bndbox>
	</object>
	<object>
		<name>coin</name>
		<pose>Unspecified</pose>
		<truncated>0</truncated>
		<difficult>0</difficult>
		<bndbox>
			<xmin>420</xmin>
			<ymin>198</ymin>
			<xmax>467</xmax>
			<ymax>245</ymax>
		</bndbox>
	</object>
</annotation>
