<annotation>
	<folder>VOC2007</folder>
	<filename>banana009T(4).JPG</filename>
	<source>
		<database>My Database</database>
		<annotation>VOC2007</annotation>
		<image>flickr</image>
		<flickrid>NULL</flickrid>
	</source>
	<owner>
		<flickrid>NULL</flickrid>
		<name>Liang-yc</name>
	</owner>
	<size>
		<width>816</width>
		<height>612</height>
		<depth>3</depth>
	</size>
	<segmented>0</segmented>
	<object>
		<name>banana</name>
		<pose>Unspecified</pose>
		<truncated>0</truncated>
		<difficult>0</difficult>
		<bndbox>
			<xmin>338</xmin>
			<ymin>50</ymin>
			<xmax>557</xmax>
			<ymax>489</ymax>
		</bndbox>
	</object>
	<object>
		<name>coin</name>
		<pose>Unspecified</pose>
		<truncated>0</truncated>
		<difficult>0</difficult>
		<bndbox>
			<xmin>191</xmin>
			<ymin>203</ymin>
			<xmax>243</xmax>
			<ymax>256</ymax>
		</bndbox>
	</object>
</annotation>
