<annotation>
	<folder>VOC2007</folder>
	<filename>lemon002S(14).JPG</filename>
	<source>
		<database>My Database</database>
		<annotation>VOC2007</annotation>
		<image>flickr</image>
		<flickrid>NULL</flickrid>
	</source>
	<owner>
		<flickrid>NULL</flickrid>
		<name>xiaoxianyu</name>
	</owner>
	<size>
		<width>816</width>
		<height>612</height>
		<depth>3</depth>
	</size>
	<segmented>0</segmented>
	<object>
		<name>lemon</name>
		<pose>Unspecified</pose>
		<truncated>0</truncated>
		<difficult>0</difficult>
		<bndbox>
			<xmin>477</xmin>
			<ymin>315</ymin>
			<xmax>607</xmax>
			<ymax>442</ymax>
		</bndbox>
	</object>
	<object>
		<name>coin</name>
		<pose>Unspecified</pose>
		<truncated>0</truncated>
		<difficult>0</difficult>
		<bndbox>
			<xmin>163</xmin>
			<ymin>397</ymin>
			<xmax>221</xmax>
			<ymax>459</ymax>
		</bndbox>
	</object>
</annotation>
